favro_cli/__init__.py
favro_cli/__main__.py
favro_cli/cli.py
favro_cli/config.py
favro_cli/api/__init__.py
favro_cli/api/client.py
favro_cli/api/models.py
favro_cli/commands/__init__.py
favro_cli/commands/auth.py
favro_cli/commands/board.py
favro_cli/commands/card.py
favro_cli/commands/column.py
favro_cli/commands/common.py
favro_cli/commands/org.py
favro_cli/output/__init__.py
favro_cli/output/formatters.py
favro_cli/resolvers/__init__.py
favro_cli/resolvers/base.py
favro_cli/resolvers/board.py
favro_cli/resolvers/card.py
favro_cli/resolvers/column.py
favro_cli/resolvers/organization.py
favro_cli/resolvers/tag.py
favro_cli/resolvers/user.py
favro_cli-0.1.6.dist-info/METADATA
favro_cli-0.1.6.dist-info/WHEEL
favro_cli-0.1.6.dist-info/entry_points.txt
favro_cli-0.1.6.dist-info/licenses/LICENSE
favro_cli-0.1.6.dist-info/RECORD
