Metadata-Version: 2.4
Name: favro-cli
Version: 0.1.6
Summary: CLI for Favro project management
Author-email: Truls Borgvall <truls.borgvall@icloud.com>
License-Expression: MIT
License-File: LICENSE
Requires-Python: >=3.12
Requires-Dist: httpx>=0.25.0
Requires-Dist: pydantic>=2.0.0
Requires-Dist: rich>=13.0.0
Requires-Dist: typer>=0.9.0
Provides-Extra: dev
Requires-Dist: pyright>=1.1.389; extra == 'dev'
Requires-Dist: pytest-asyncio>=0.24; extra == 'dev'
Requires-Dist: pytest>=8.0; extra == 'dev'
